pynut3/__init__.py
pynut3/nut3.py
pynut3/py.typed
pynut3/demoups.py
pynut3-2.2.1.dist-info/METADATA
pynut3-2.2.1.dist-info/WHEEL
pynut3-2.2.1.dist-info/entry_points.txt
pynut3-2.2.1.dist-info/licenses/LICENSE
pynut3-2.2.1.dist-info/RECORD
