Metadata-Version: 2.1
Name: pynut3
Version: 2.2.1
Summary: A Python3 abstraction class to access NUT servers for uninterruptible power supplies (UPS).
Project-URL: Homepage, https://github.com/Mausy5043/python-nut3
Project-URL: Bug Tracker, https://github.com/Mausy5043/python-nut3/issues
Author: Mausy5043
License-Expression: GPL-3.0-only
License-File: LICENSE
Classifier: Development Status :: 5 - Production/Stable
Classifier: License :: OSI Approved :: GNU General Public License v3 (GPLv3)
Classifier: Operating System :: OS Independent
Classifier: Programming Language :: Python :: 3.9
Classifier: Programming Language :: Python :: 3.10
Classifier: Programming Language :: Python :: 3.11
Classifier: Programming Language :: Python :: 3.12
Classifier: Topic :: System :: Power (UPS)
Requires-Python: >=3.9
Requires-Dist: pexpect
